{
  "qProperty": {
    "qInfo": {
      "qId": "d4ac421a-13d2-494f-a7b7-777850c685d5",
      "qType": "sheet"
    },
    "qMetaDef": {
      "title": "ПОРТФЕЛЬ ПО СЕГМЕНТАМ",
      "description": ""
    },
    "rank": -1,
    "thumbnail": {
      "qStaticContentUrlDef": {}
    },
    "columns": 24,
    "rows": 12,
    "cells": [
      {
        "name": "EhVFjd",
        "type": "table",
        "col": 3,
        "row": 0,
        "colspan": 9,
        "rowspan": 6,
        "bounds": {
          "y": 0,
          "x": 12.5,
          "width": 37.5,
          "height": 50
        }
      },
      {
        "name": "eDBh",
        "type": "table",
        "col": 12,
        "row": 0,
        "colspan": 12,
        "rowspan": 6,
        "bounds": {
          "y": 0,
          "x": 50,
          "width": 50,
          "height": 50
        }
      },
      {
        "name": "UMzh",
        "type": "filterpane",
        "col": 0,
        "row": 0,
        "colspan": 3,
        "rowspan": 6,
        "bounds": {
          "y": 0,
          "x": 0,
          "width": 12.5,
          "height": 50
        }
      }
    ],
    "qChildListDef": {
      "qData": {
        "title": "/title"
      }
    },
    "gridResolution": "small"
  },
  "qChildren": [
    {
      "qProperty": {
        "qInfo": {
          "qId": "EhVFjd",
          "qType": "table"
        },
        "qMetaDef": {},
        "qHyperCubeDef": {
          "qDimensions": [
            {
              "qDef": {
                "qGrouping": "N",
                "qFieldDefs": [
                  "ДАТА СРЕЗА"
                ],
                "qFieldLabels": [
                  ""
                ],
                "qSortCriterias": [
                  {
                    "qSortByNumeric": 1,
                    "qSortByAscii": 1,
                    "qSortByLoadOrder": 1,
                    "qExpression": {}
                  }
                ],
                "qNumberPresentations": [],
                "qActiveField": 0,
                "autoSort": true,
                "cId": "NtTx",
                "othersLabel": "Others",
                "textAlign": {
                  "auto": true,
                  "align": "left"
                },
                "representation": {
                  "type": "text",
                  "urlPosition": "dimension",
                  "urlLabel": "",
                  "linkUrl": ""
                }
              },
              "qOtherTotalSpec": {
                "qOtherMode": "OTHER_OFF",
                "qOtherCounted": {
                  "qv": "10"
                },
                "qOtherLimit": {
                  "qv": "0"
                },
                "qOtherLimitMode": "OTHER_GE_LIMIT",
                "qForceBadValueKeeping": true,
                "qApplyEvenWhenPossiblyWrongResult": true,
                "qOtherSortMode": "OTHER_SORT_DESCENDING",
                "qTotalMode": "TOTAL_OFF",
                "qReferencedExpression": {}
              },
              "qOtherLabel": {
                "qv": "Others"
              },
              "qTotalLabel": {},
              "qCalcCond": {},
              "qAttributeExpressions": [],
              "qAttributeDimensions": [],
              "qCalcCondition": {
                "qCond": {},
                "qMsg": {}
              }
            },
            {
              "qDef": {
                "qGrouping": "N",
                "qFieldDefs": [
                  "PROVIDER_ID"
                ],
                "qFieldLabels": [
                  ""
                ],
                "qSortCriterias": [
                  {
                    "qSortByNumeric": 1,
                    "qSortByAscii": 1,
                    "qSortByLoadOrder": 1,
                    "qExpression": {}
                  }
                ],
                "qNumberPresentations": [],
                "qActiveField": 0,
                "autoSort": true,
                "cId": "ybGaX",
                "othersLabel": "Others",
                "textAlign": {
                  "auto": true,
                  "align": "left"
                },
                "representation": {
                  "type": "text",
                  "urlPosition": "dimension",
                  "urlLabel": "",
                  "linkUrl": ""
                }
              },
              "qOtherTotalSpec": {
                "qOtherMode": "OTHER_OFF",
                "qOtherCounted": {
                  "qv": "10"
                },
                "qOtherLimit": {
                  "qv": "0"
                },
                "qOtherLimitMode": "OTHER_GE_LIMIT",
                "qForceBadValueKeeping": true,
                "qApplyEvenWhenPossiblyWrongResult": true,
                "qOtherSortMode": "OTHER_SORT_DESCENDING",
                "qTotalMode": "TOTAL_OFF",
                "qReferencedExpression": {}
              },
              "qOtherLabel": {
                "qv": "Others"
              },
              "qTotalLabel": {},
              "qCalcCond": {},
              "qAttributeExpressions": [],
              "qAttributeDimensions": [],
              "qCalcCondition": {
                "qCond": {},
                "qMsg": {}
              }
            },
            {
              "qDef": {
                "qGrouping": "N",
                "qFieldDefs": [
                  "СЕГМЕНТ"
                ],
                "qFieldLabels": [
                  ""
                ],
                "qSortCriterias": [
                  {
                    "qSortByNumeric": 1,
                    "qSortByAscii": 1,
                    "qSortByLoadOrder": 1,
                    "qExpression": {}
                  }
                ],
                "qNumberPresentations": [],
                "qActiveField": 0,
                "autoSort": true,
                "cId": "DjPhQk",
                "othersLabel": "Others",
                "textAlign": {
                  "auto": true,
                  "align": "left"
                },
                "representation": {
                  "type": "text",
                  "urlPosition": "dimension",
                  "urlLabel": "",
                  "linkUrl": ""
                }
              },
              "qOtherTotalSpec": {
                "qOtherMode": "OTHER_OFF",
                "qOtherCounted": {
                  "qv": "10"
                },
                "qOtherLimit": {
                  "qv": "0"
                },
                "qOtherLimitMode": "OTHER_GE_LIMIT",
                "qForceBadValueKeeping": true,
                "qApplyEvenWhenPossiblyWrongResult": true,
                "qOtherSortMode": "OTHER_SORT_DESCENDING",
                "qTotalMode": "TOTAL_OFF",
                "qReferencedExpression": {}
              },
              "qOtherLabel": {
                "qv": "Others"
              },
              "qTotalLabel": {},
              "qCalcCond": {},
              "qAttributeExpressions": [],
              "qAttributeDimensions": [],
              "qCalcCondition": {
                "qCond": {},
                "qMsg": {}
              }
            }
          ],
          "qMeasures": [
            {
              "qDef": {
                "qTags": [],
                "qGrouping": "N",
                "qDef": "Sum([СУММА ЗАДОЛЖЕННОСТИ])",
                "qNumFormat": {
                  "qType": "U",
                  "qnDec": 10,
                  "qUseThou": 0
                },
                "qAggrFunc": "Expr",
                "qAccumulate": 0,
                "qActiveExpression": 0,
                "qExpressions": [],
                "autoSort": true,
                "cId": "YPruGCS",
                "numFormatFromTemplate": true,
                "textAlign": {
                  "auto": true,
                  "align": "left"
                },
                "representation": {
                  "type": "text",
                  "indicator": {
                    "showTextValues": true,
                    "applySegmentColors": false,
                    "position": "right"
                  },
                  "miniChart": {
                    "type": "sparkline",
                    "colors": {
                      "main": {
                        "index": 6
                      },
                      "max": {
                        "index": 0,
                        "color": "none"
                      },
                      "min": {
                        "index": 0,
                        "color": "none"
                      },
                      "first": {
                        "index": 0,
                        "color": "none"
                      },
                      "last": {
                        "index": 0,
                        "color": "none"
                      },
                      "positive": {
                        "index": 6
                      },
                      "negative": {
                        "index": 10,
                        "color": "#f93f17"
                      }
                    },
                    "showDots": true,
                    "yAxis": {
                      "scale": "local",
                      "position": "auto"
                    }
                  }
                },
                "conditionalColoring": {
                  "segments": {
                    "limits": [],
                    "paletteColors": [
                      {
                        "index": 6,
                        "icon": "dot"
                      }
                    ]
                  }
                }
              },
              "qSortBy": {
                "qSortByNumeric": -1,
                "qSortByLoadOrder": 1,
                "qExpression": {}
              },
              "qAttributeExpressions": [],
              "qAttributeDimensions": [],
              "qCalcCond": {},
              "qCalcCondition": {
                "qCond": {},
                "qMsg": {}
              },
              "qTrendLines": [],
              "qMiniChartDef": {
                "qSortBy": {
                  "qExpression": {}
                },
                "qOtherTotalSpec": {
                  "qOtherMode": "OTHER_OFF",
                  "qOtherCounted": {},
                  "qOtherLimit": {},
                  "qOtherLimitMode": "OTHER_GT_LIMIT",
                  "qSuppressOther": true,
                  "qForceBadValueKeeping": true,
                  "qApplyEvenWhenPossiblyWrongResult": true,
                  "qOtherSortMode": "OTHER_SORT_DESCENDING",
                  "qTotalMode": "TOTAL_OFF",
                  "qReferencedExpression": {}
                },
                "qMaxNumberPoints": -1,
                "qAttributeExpressions": [],
                "qNullSuppression": true
              }
            }
          ],
          "qInterColumnSortOrder": [
            1,
            2,
            3,
            0
          ],
          "qSuppressMissing": true,
          "qInitialDataFetch": [],
          "qReductionMode": "N",
          "qMode": "S",
          "qPseudoDimPos": -1,
          "qNoOfLeftDims": -1,
          "qMaxStackedCells": 5000,
          "qCalcCond": {},
          "qTitle": {},
          "qCalcCondition": {
            "qCond": {},
            "qMsg": {}
          },
          "qColumnOrder": [
            0,
            1,
            2,
            3
          ],
          "qExpansionState": [],
          "columnOrder": [
            0,
            1,
            2,
            3
          ],
          "columnWidths": [
            -1,
            -1,
            -1,
            -1
          ],
          "qLayoutExclude": {
            "qHyperCubeDef": {
              "qDimensions": [],
              "qMeasures": [],
              "qInterColumnSortOrder": [],
              "qInitialDataFetch": [],
              "qReductionMode": "N",
              "qMode": "S",
              "qPseudoDimPos": -1,
              "qNoOfLeftDims": -1,
              "qMaxStackedCells": 5000,
              "qCalcCond": {},
              "qTitle": {},
              "qCalcCondition": {
                "qCond": {},
                "qMsg": {}
              },
              "qColumnOrder": [],
              "qExpansionState": []
            }
          }
        },
        "search": {
          "sorting": "auto"
        },
        "showTitles": true,
        "title": "В РАЗРЕЗЕ СЕГМЕНТОВ",
        "subtitle": "",
        "footnote": "",
        "disableNavMenu": false,
        "showDetails": false,
        "components": [],
        "totals": {
          "show": true,
          "position": "noTotals",
          "label": "Totals"
        },
        "scrolling": {
          "horizontal": true,
          "keepFirstColumnInView": false,
          "keepFirstColumnInViewTouch": false
        },
        "multiline": {
          "wrapTextInHeaders": true,
          "wrapTextInCells": true
        },
        "visualization": "table"
      },
      "qChildren": []
    },
    {
      "qProperty": {
        "qInfo": {
          "qId": "eDBh",
          "qType": "table"
        },
        "qMetaDef": {},
        "qHyperCubeDef": {
          "qDimensions": [
            {
              "qDef": {
                "qGrouping": "N",
                "qFieldDefs": [
                  "ДАТА СРЕЗА"
                ],
                "qFieldLabels": [
                  ""
                ],
                "qSortCriterias": [
                  {
                    "qSortByNumeric": 1,
                    "qSortByAscii": 1,
                    "qSortByLoadOrder": 1,
                    "qExpression": {}
                  }
                ],
                "qNumberPresentations": [],
                "qActiveField": 0,
                "autoSort": true,
                "cId": "Snx",
                "othersLabel": "Others",
                "textAlign": {
                  "auto": true,
                  "align": "left"
                },
                "representation": {
                  "type": "text",
                  "urlPosition": "dimension",
                  "urlLabel": "",
                  "linkUrl": ""
                }
              },
              "qOtherTotalSpec": {
                "qOtherMode": "OTHER_OFF",
                "qOtherCounted": {
                  "qv": "10"
                },
                "qOtherLimit": {
                  "qv": "0"
                },
                "qOtherLimitMode": "OTHER_GE_LIMIT",
                "qForceBadValueKeeping": true,
                "qApplyEvenWhenPossiblyWrongResult": true,
                "qOtherSortMode": "OTHER_SORT_DESCENDING",
                "qTotalMode": "TOTAL_OFF",
                "qReferencedExpression": {}
              },
              "qOtherLabel": {
                "qv": "Others"
              },
              "qTotalLabel": {},
              "qCalcCond": {},
              "qAttributeExpressions": [],
              "qAttributeDimensions": [],
              "qCalcCondition": {
                "qCond": {},
                "qMsg": {}
              }
            },
            {
              "qDef": {
                "qGrouping": "N",
                "qFieldDefs": [
                  "PROVIDER_ID"
                ],
                "qFieldLabels": [
                  ""
                ],
                "qSortCriterias": [
                  {
                    "qSortByNumeric": 1,
                    "qSortByAscii": 1,
                    "qSortByLoadOrder": 1,
                    "qExpression": {}
                  }
                ],
                "qNumberPresentations": [],
                "qActiveField": 0,
                "autoSort": true,
                "cId": "PqtWC",
                "othersLabel": "Others",
                "textAlign": {
                  "auto": true,
                  "align": "left"
                },
                "representation": {
                  "type": "text",
                  "urlPosition": "dimension",
                  "urlLabel": "",
                  "linkUrl": ""
                }
              },
              "qOtherTotalSpec": {
                "qOtherMode": "OTHER_OFF",
                "qOtherCounted": {
                  "qv": "10"
                },
                "qOtherLimit": {
                  "qv": "0"
                },
                "qOtherLimitMode": "OTHER_GE_LIMIT",
                "qForceBadValueKeeping": true,
                "qApplyEvenWhenPossiblyWrongResult": true,
                "qOtherSortMode": "OTHER_SORT_DESCENDING",
                "qTotalMode": "TOTAL_OFF",
                "qReferencedExpression": {}
              },
              "qOtherLabel": {
                "qv": "Others"
              },
              "qTotalLabel": {},
              "qCalcCond": {},
              "qAttributeExpressions": [],
              "qAttributeDimensions": [],
              "qCalcCondition": {
                "qCond": {},
                "qMsg": {}
              }
            }
          ],
          "qMeasures": [
            {
              "qDef": {
                "qTags": [],
                "qGrouping": "N",
                "qDef": "Sum([СУММА ЗАДОЛЖЕННОСТИ])",
                "qNumFormat": {
                  "qType": "U",
                  "qnDec": 10,
                  "qUseThou": 0
                },
                "qAggrFunc": "Expr",
                "qAccumulate": 0,
                "qActiveExpression": 0,
                "qExpressions": [],
                "autoSort": true,
                "cId": "YpzKKmv",
                "numFormatFromTemplate": true,
                "textAlign": {
                  "auto": true,
                  "align": "left"
                },
                "representation": {
                  "type": "text",
                  "indicator": {
                    "showTextValues": true,
                    "applySegmentColors": false,
                    "position": "right"
                  },
                  "miniChart": {
                    "type": "sparkline",
                    "colors": {
                      "main": {
                        "index": 6
                      },
                      "max": {
                        "index": 0,
                        "color": "none"
                      },
                      "min": {
                        "index": 0,
                        "color": "none"
                      },
                      "first": {
                        "index": 0,
                        "color": "none"
                      },
                      "last": {
                        "index": 0,
                        "color": "none"
                      },
                      "positive": {
                        "index": 6
                      },
                      "negative": {
                        "index": 10,
                        "color": "#f93f17"
                      }
                    },
                    "showDots": true,
                    "yAxis": {
                      "scale": "local",
                      "position": "auto"
                    }
                  }
                },
                "conditionalColoring": {
                  "segments": {
                    "limits": [],
                    "paletteColors": [
                      {
                        "index": 6,
                        "icon": "dot"
                      }
                    ]
                  }
                }
              },
              "qSortBy": {
                "qSortByNumeric": -1,
                "qSortByLoadOrder": 1,
                "qExpression": {}
              },
              "qAttributeExpressions": [],
              "qAttributeDimensions": [],
              "qCalcCond": {},
              "qCalcCondition": {
                "qCond": {},
                "qMsg": {}
              },
              "qTrendLines": [],
              "qMiniChartDef": {
                "qSortBy": {
                  "qExpression": {}
                },
                "qOtherTotalSpec": {
                  "qOtherMode": "OTHER_OFF",
                  "qOtherCounted": {},
                  "qOtherLimit": {},
                  "qOtherLimitMode": "OTHER_GT_LIMIT",
                  "qSuppressOther": true,
                  "qForceBadValueKeeping": true,
                  "qApplyEvenWhenPossiblyWrongResult": true,
                  "qOtherSortMode": "OTHER_SORT_DESCENDING",
                  "qTotalMode": "TOTAL_OFF",
                  "qReferencedExpression": {}
                },
                "qMaxNumberPoints": -1,
                "qAttributeExpressions": [],
                "qNullSuppression": true
              }
            }
          ],
          "qInterColumnSortOrder": [
            0,
            1,
            2
          ],
          "qSuppressMissing": true,
          "qInitialDataFetch": [],
          "qReductionMode": "N",
          "qMode": "S",
          "qPseudoDimPos": -1,
          "qNoOfLeftDims": -1,
          "qMaxStackedCells": 5000,
          "qCalcCond": {},
          "qTitle": {},
          "qCalcCondition": {
            "qCond": {},
            "qMsg": {}
          },
          "qColumnOrder": [
            0,
            1,
            2
          ],
          "qExpansionState": [],
          "columnOrder": [
            0,
            1,
            2
          ],
          "columnWidths": [
            -1,
            -1,
            -1
          ],
          "qLayoutExclude": {
            "qHyperCubeDef": {
              "qDimensions": [],
              "qMeasures": [],
              "qInterColumnSortOrder": [],
              "qInitialDataFetch": [],
              "qReductionMode": "N",
              "qMode": "S",
              "qPseudoDimPos": -1,
              "qNoOfLeftDims": -1,
              "qMaxStackedCells": 5000,
              "qCalcCond": {},
              "qTitle": {},
              "qCalcCondition": {
                "qCond": {},
                "qMsg": {}
              },
              "qColumnOrder": [],
              "qExpansionState": []
            }
          }
        },
        "search": {
          "sorting": "auto"
        },
        "showTitles": true,
        "title": "",
        "subtitle": "",
        "footnote": "",
        "disableNavMenu": false,
        "showDetails": false,
        "components": [],
        "totals": {
          "show": true,
          "position": "noTotals",
          "label": "Totals"
        },
        "scrolling": {
          "horizontal": true,
          "keepFirstColumnInView": false,
          "keepFirstColumnInViewTouch": false
        },
        "multiline": {
          "wrapTextInHeaders": true,
          "wrapTextInCells": true
        },
        "visualization": "table"
      },
      "qChildren": []
    },
    {
      "qProperty": {
        "qInfo": {
          "qId": "UMzh",
          "qType": "filterpane"
        },
        "qMetaDef": {},
        "qChildListDef": {
          "qData": {
            "info": "/qInfo"
          }
        },
        "showTitles": false,
        "title": "",
        "subtitle": "",
        "footnote": "",
        "disableNavMenu": false,
        "showDetails": false,
        "visualization": "filterpane"
      },
      "qChildren": [
        {
          "qProperty": {
            "qInfo": {
              "qId": "75805043-ee11-48d6-b7dc-7f0857ebc18f",
              "qType": "listbox"
            },
            "qMetaDef": {},
            "qListObjectDef": {
              "qDef": {
                "qGrouping": "N",
                "qFieldDefs": [
                  "СЕГМЕНТ"
                ],
                "qFieldLabels": [
                  "СЕГМЕНТ"
                ],
                "qSortCriterias": [
                  {
                    "qSortByState": 1,
                    "qSortByNumeric": 1,
                    "qSortByAscii": 1,
                    "qSortByLoadOrder": 1,
                    "qExpression": {}
                  }
                ],
                "qNumberPresentations": [],
                "qActiveField": 0,
                "autoSort": true,
                "cId": "kAPnHP"
              },
              "qFrequencyMode": "N",
              "qShowAlternatives": true,
              "qInitialDataFetch": [],
              "qExpressions": [],
              "qOtherTotalSpec": {}
            },
            "showTitles": true,
            "title": "СЕГМЕНТ",
            "subtitle": "",
            "footnote": "",
            "disableNavMenu": false,
            "showDetails": false,
            "visualization": "listbox"
          },
          "qChildren": []
        }
      ]
    }
  ]
}